sshg.py
sshg-0.1.5.dist-info/LICENSE
sshg-0.1.5.dist-info/METADATA
sshg-0.1.5.dist-info/WHEEL
sshg-0.1.5.dist-info/entry_points.txt
sshg-0.1.5.dist-info/RECORD
