Metadata-Version: 2.1
Name: sshg
Version: 0.1.5
Summary: ssh from config with arrow select support
Home-page: https://github.com/codeskyblue/sshg
License: MIT
Author: codeskyblue
Author-email: codeskyblue@gmail.com
Requires-Python: >=3.8,<4.0
Classifier: License :: OSI Approved :: MIT License
Classifier: Programming Language :: Python :: 3
Classifier: Programming Language :: Python :: 3.8
Classifier: Programming Language :: Python :: 3.9
Classifier: Programming Language :: Python :: 3.10
Classifier: Programming Language :: Python :: 3.11
Requires-Dist: Jinja2 (>=3.1.2,<4.0.0)
Requires-Dist: dataclasses-json
Requires-Dist: pexpect
Requires-Dist: prompt_toolkit
Requires-Dist: pyyaml
Requires-Dist: requests
